vyhaocalculator/__init__.py
HaoCalculator-0.0.1.dist-info/LICENSE.txt
HaoCalculator-0.0.1.dist-info/METADATA
HaoCalculator-0.0.1.dist-info/WHEEL
HaoCalculator-0.0.1.dist-info/top_level.txt
HaoCalculator-0.0.1.dist-info/RECORD
